sunchun_mpc_test_001/__init__.py
sunchun_mpc_test_001/server.py
sunchun_mpc_test_001-0.1.0.dist-info/METADATA
sunchun_mpc_test_001-0.1.0.dist-info/WHEEL
sunchun_mpc_test_001-0.1.0.dist-info/entry_points.txt
sunchun_mpc_test_001-0.1.0.dist-info/RECORD
