Metadata-Version: 2.4
Name: sunchun-mpc-test-001
Version: 0.1.0
Summary: Add your description here
Requires-Python: >=3.11
Requires-Dist: build>=1.3.0
Requires-Dist: mcp[cli]>=1.24.0
Requires-Dist: twine>=6.2.0
